[{"it5tot514": 13, "it5wins514": 9, "name": "Wukong", "it3wins514": 5, "it4wins514": 2, "it3tot514": 7, "champion_id": 62, "matchversion": "5.14", "it0tot514": 178, "version": "6.1.1", "it2wins514": 40, "it0wins514": 107, "it4tot514": 2, "it2tot514": 80, "it1tot514": 235, "region": "LAS", "it1wins514": 123}, {"it5tot514": 3, "it5wins514": 3, "name": "Jax", "it3wins514": 3, "it4wins514": 0, "it3tot514": 3, "champion_id": 24, "matchversion": "5.14", "it0tot514": 29, "version": "6.1.1", "it2wins514": 18, "it0wins514": 13, "it4tot514": 1, "it2tot514": 28, "it1tot514": 39, "region": "LAS", "it1wins514": 22}, {"it5tot514": 8, "it5wins514": 6, "name": "Shaco", "it3wins514": 2, "it4wins514": 1, "it3tot514": 5, "champion_id": 35, "matchversion": "5.14", "it0tot514": 142, "version": "6.1.1", "it2wins514": 53, "it0wins514": 73, "it4tot514": 1, "it2tot514": 94, "it1tot514": 203, "region": "LAS", "it1wins514": 105}, {"it5tot514": 0, "it5wins514": 0, "name": "Warwick", "it3wins514": 0, "it4wins514": 0, "it3tot514": 0, "champion_id": 19, "matchversion": "5.14", "it0tot514": 1, "version": "6.1.1", "it2wins514": 1, "it0wins514": 0, "it4tot514": 0, "it2tot514": 1, "it1tot514": 7, "region": "LAS", "it1wins514": 4}, {"it5tot514": 4, "it5wins514": 4, "name": "Tryndamere", "it3wins514": 0, "it4wins514": 0, "it3tot514": 1, "champion_id": 23, "matchversion": "5.14", "it0tot514": 20, "version": "6.1.1", "it2wins514": 7, "it0wins514": 9, "it4tot514": 0, "it2tot514": 8, "it1tot514": 23, "region": "LAS", "it1wins514": 12}, {"it5tot514": 31, "it5wins514": 15, "name": "Riven", "it3wins514": 6, "it4wins514": 2, "it3tot514": 13, "champion_id": 92, "matchversion": "5.14", "it0tot514": 490, "version": "6.1.1", "it2wins514": 111, "it0wins514": 281, "it4tot514": 5, "it2tot514": 209, "it1tot514": 568, "region": "LAS", "it1wins514": 319}, {"it5tot514": 0, "it5wins514": 0, "name": "Gangplank", "it3wins514": 0, "it4wins514": 1, "it3tot514": 1, "champion_id": 41, "matchversion": "5.14", "it0tot514": 18, "version": "6.1.1", "it2wins514": 3, "it0wins514": 11, "it4tot514": 1, "it2tot514": 5, "it1tot514": 21, "region": "LAS", "it1wins514": 9}, {"it5tot514": 0, "it5wins514": 0, "name": "Poppy", "it3wins514": 0, "it4wins514": 0, "it3tot514": 0, "champion_id": 78, "matchversion": "5.14", "it0tot514": 9, "version": "6.1.1", "it2wins514": 1, "it0wins514": 6, "it4tot514": 0, "it2tot514": 3, "it1tot514": 4, "region": "LAS", "it1wins514": 3}, {"it5tot514": 0, "it5wins514": 0, "name": "Trundle", "it3wins514": 0, "it4wins514": 0, "it3tot514": 0, "champion_id": 48, "matchversion": "5.14", "it0tot514": 13, "version": "6.1.1", "it2wins514": 5, "it0wins514": 7, "it4tot514": 0, "it2tot514": 7, "it1tot514": 8, "region": "LAS", "it1wins514": 6}, {"it5tot514": 1, "it5wins514": 0, "name": "Shyvana", "it3wins514": 0, "it4wins514": 2, "it3tot514": 0, "champion_id": 102, "matchversion": "5.14", "it0tot514": 29, "version": "6.1.1", "it2wins514": 11, "it0wins514": 21, "it4tot514": 3, "it2tot514": 19, "it1tot514": 40, "region": "LAS", "it1wins514": 22}, {"it5tot514": 7, "it5wins514": 3, "name": "Renekton", "it3wins514": 2, "it4wins514": 1, "it3tot514": 8, "champion_id": 58, "matchversion": "5.14", "it0tot514": 192, "version": "6.1.1", "it2wins514": 51, "it0wins514": 116, "it4tot514": 1, "it2tot514": 79, "it1tot514": 230, "region": "LAS", "it1wins514": 123}, {"it5tot514": 6, "it5wins514": 4, "name": "Fiora", "it3wins514": 6, "it4wins514": 1, "it3tot514": 8, "champion_id": 114, "matchversion": "5.14", "it0tot514": 216, "version": "6.1.1", "it2wins514": 45, "it0wins514": 118, "it4tot514": 1, "it2tot514": 77, "it1tot514": 230, "region": "LAS", "it1wins514": 125}, {"it5tot514": 2, "it5wins514": 2, "name": "Kha'Zix", "it3wins514": 3, "it4wins514": 0, "it3tot514": 3, "champion_id": 121, "matchversion": "5.14", "it0tot514": 102, "version": "6.1.1", "it2wins514": 22, "it0wins514": 55, "it4tot514": 0, "it2tot514": 45, "it1tot514": 95, "region": "LAS", "it1wins514": 43}, {"it5tot514": 4, "it5wins514": 2, "name": "Olaf", "it3wins514": 3, "it4wins514": 0, "it3tot514": 6, "champion_id": 2, "matchversion": "5.14", "it0tot514": 36, "version": "6.1.1", "it2wins514": 8, "it0wins514": 20, "it4tot514": 0, "it2tot514": 20, "it1tot514": 49, "region": "LAS", "it1wins514": 25}, {"it5tot514": 2, "it5wins514": 1, "name": "Yasuo", "it3wins514": 1, "it4wins514": 0, "it3tot514": 1, "champion_id": 157, "matchversion": "5.14", "it0tot514": 7, "version": "6.1.1", "it2wins514": 3, "it0wins514": 3, "it4tot514": 0, "it2tot514": 9, "it1tot514": 10, "region": "LAS", "it1wins514": 8}, {"it5tot514": 19, "it5wins514": 11, "name": "Rengar", "it3wins514": 5, "it4wins514": 3, "it3tot514": 6, "champion_id": 107, "matchversion": "5.14", "it0tot514": 226, "version": "6.1.1", "it2wins514": 66, "it0wins514": 123, "it4tot514": 3, "it2tot514": 117, "it1tot514": 272, "region": "LAS", "it1wins514": 145}, {"it5tot514": 3, "it5wins514": 1, "name": "Pantheon", "it3wins514": 1, "it4wins514": 3, "it3tot514": 5, "champion_id": 80, "matchversion": "5.14", "it0tot514": 187, "version": "6.1.1", "it2wins514": 32, "it0wins514": 97, "it4tot514": 3, "it2tot514": 63, "it1tot514": 201, "region": "LAS", "it1wins514": 100}, {"it5tot514": 3, "it5wins514": 2, "name": "Sion", "it3wins514": 1, "it4wins514": 0, "it3tot514": 1, "champion_id": 14, "matchversion": "5.14", "it0tot514": 17, "version": "6.1.1", "it2wins514": 6, "it0wins514": 8, "it4tot514": 0, "it2tot514": 9, "it1tot514": 13, "region": "LAS", "it1wins514": 9}, {"it5tot514": 3, "it5wins514": 1, "name": "Udyr", "it3wins514": 0, "it4wins514": 0, "it3tot514": 1, "champion_id": 77, "matchversion": "5.14", "it0tot514": 6, "version": "6.1.1", "it2wins514": 6, "it0wins514": 2, "it4tot514": 0, "it2tot514": 9, "it1tot514": 19, "region": "LAS", "it1wins514": 11}, {"it5tot514": 8, "it5wins514": 5, "name": "Darius", "it3wins514": 8, "it4wins514": 0, "it3tot514": 13, "champion_id": 122, "matchversion": "5.14", "it0tot514": 241, "version": "6.1.1", "it2wins514": 31, "it0wins514": 139, "it4tot514": 1, "it2tot514": 64, "it1tot514": 219, "region": "LAS", "it1wins514": 117}, {"it5tot514": 0, "it5wins514": 0, "name": "Nocturne", "it3wins514": 0, "it4wins514": 1, "it3tot514": 0, "champion_id": 56, "matchversion": "5.14", "it0tot514": 13, "version": "6.1.1", "it2wins514": 7, "it0wins514": 7, "it4tot514": 2, "it2tot514": 12, "it1tot514": 22, "region": "LAS", "it1wins514": 13}, {"it5tot514": 0, "it5wins514": 0, "name": "Master Yi", "it3wins514": 2, "it4wins514": 1, "it3tot514": 3, "champion_id": 11, "matchversion": "5.14", "it0tot514": 29, "version": "6.1.1", "it2wins514": 11, "it0wins514": 11, "it4tot514": 2, "it2tot514": 20, "it1tot514": 27, "region": "LAS", "it1wins514": 13}, {"it5tot514": 3, "it5wins514": 2, "name": "Aatrox", "it3wins514": 4, "it4wins514": 1, "it3tot514": 5, "champion_id": 266, "matchversion": "5.14", "it0tot514": 61, "version": "6.1.1", "it2wins514": 26, "it0wins514": 42, "it4tot514": 1, "it2tot514": 35, "it1tot514": 75, "region": "LAS", "it1wins514": 43}, {"it5tot514": 9, "it5wins514": 6, "name": "Talon", "it3wins514": 3, "it4wins514": 0, "it3tot514": 5, "champion_id": 91, "matchversion": "5.14", "it0tot514": 128, "version": "6.1.1", "it2wins514": 52, "it0wins514": 70, "it4tot514": 2, "it2tot514": 82, "it1tot514": 168, "region": "LAS", "it1wins514": 79}, {"it5tot514": 1, "it5wins514": 1, "name": "Xin Zhao", "it3wins514": 4, "it4wins514": 0, "it3tot514": 6, "champion_id": 5, "matchversion": "5.14", "it0tot514": 29, "version": "6.1.1", "it2wins514": 14, "it0wins514": 20, "it4tot514": 0, "it2tot514": 23, "it1tot514": 49, "region": "LAS", "it1wins514": 30}, {"it5tot514": 7, "it5wins514": 5, "name": "Lee Sin", "it3wins514": 5, "it4wins514": 2, "it3tot514": 9, "champion_id": 64, "matchversion": "5.14", "it0tot514": 209, "version": "6.1.1", "it2wins514": 57, "it0wins514": 105, "it4tot514": 6, "it2tot514": 106, "it1tot514": 187, "region": "LAS", "it1wins514": 105}, {"it5tot514": 1, "it5wins514": 0, "name": "Rek'Sai", "it3wins514": 2, "it4wins514": 0, "it3tot514": 3, "champion_id": 421, "matchversion": "5.14", "it0tot514": 53, "version": "6.1.1", "it2wins514": 13, "it0wins514": 30, "it4tot514": 0, "it2tot514": 26, "it1tot514": 56, "region": "LAS", "it1wins514": 31}, {"it5tot514": 1, "it5wins514": 1, "name": "Jarvan IV", "it3wins514": 1, "it4wins514": 1, "it3tot514": 4, "champion_id": 59, "matchversion": "5.14", "it0tot514": 85, "version": "6.1.1", "it2wins514": 15, "it0wins514": 50, "it4tot514": 1, "it2tot514": 30, "it1tot514": 80, "region": "LAS", "it1wins514": 43}, {"it5tot514": 3, "it5wins514": 2, "name": "Zed", "it3wins514": 3, "it4wins514": 0, "it3tot514": 6, "champion_id": 238, "matchversion": "5.14", "it0tot514": 29, "version": "6.1.1", "it2wins514": 15, "it0wins514": 12, "it4tot514": 0, "it2tot514": 26, "it1tot514": 45, "region": "LAS", "it1wins514": 22}]