[{"version": "6.1.1", "it4winrate511": 0.5490196078431373, "it3winrate511": 0.5862068965517241, "it1tot511": 11, "it0wins511": 2, "it3wins511": 17, "it5wins511": 15, "it4wins511": 28, "champion_id": 53, "it3tot511": 29, "it2wins511": 7, "it1winrate511": 0.45454545454545453, "it4tot511": 51, "it5tot511": 30, "it0tot511": 4, "it2tot511": 14, "name": "Blitzcrank", "matchversion": "5.11", "region": "KR", "it2winrate511": 0.5, "it1wins511": 5, "it5winrate511": 0.5, "it0winrate511": 0.5}, {"version": "6.1.1", "it4winrate511": 0.375, "it3winrate511": 0.6666666666666666, "it1tot511": 1, "it0wins511": 0, "it3wins511": 2, "it5wins511": 2, "it4wins511": 3, "champion_id": 54, "it3tot511": 3, "it2wins511": 0, "it1winrate511": 1.0, "it4tot511": 8, "it5tot511": 3, "it0tot511": 0, "it2tot511": 0, "name": "Malphite", "matchversion": "5.11", "region": "KR", "it2winrate511": 0, "it1wins511": 1, "it5winrate511": 0.6666666666666666, "it0winrate511": 0}, {"version": "6.1.1", "it4winrate511": 0.4, "it3winrate511": 0.0, "it1tot511": 0, "it0wins511": 0, "it3wins511": 0, "it5wins511": 5, "it4wins511": 2, "champion_id": 37, "it3tot511": 2, "it2wins511": 0, "it1winrate511": 0, "it4tot511": 5, "it5tot511": 8, "it0tot511": 0, "it2tot511": 0, "name": "Sona", "matchversion": "5.11", "region": "KR", "it2winrate511": 0, "it1wins511": 0, "it5winrate511": 0.625, "it0winrate511": 0}, {"version": "6.1.1", "it4winrate511": 0.5833333333333334, "it3winrate511": 0.46153846153846156, "it1tot511": 3, "it0wins511": 1, "it3wins511": 6, "it5wins511": 3, "it4wins511": 7, "champion_id": 75, "it3tot511": 13, "it2wins511": 2, "it1winrate511": 0.3333333333333333, "it4tot511": 12, "it5tot511": 9, "it0tot511": 3, "it2tot511": 5, "name": "Nasus", "matchversion": "5.11", "region": "KR", "it2winrate511": 0.4, "it1wins511": 1, "it5winrate511": 0.3333333333333333, "it0winrate511": 0.3333333333333333}, {"version": "6.1.1", "it4winrate511": 0.8, "it3winrate511": 0.2, "it1tot511": 1, "it0wins511": 0, "it3wins511": 1, "it5wins511": 6, "it4wins511": 8, "champion_id": 12, "it3tot511": 5, "it2wins511": 4, "it1winrate511": 0.0, "it4tot511": 10, "it5tot511": 8, "it0tot511": 1, "it2tot511": 4, "name": "Alistar", "matchversion": "5.11", "region": "KR", "it2winrate511": 1.0, "it1wins511": 0, "it5winrate511": 0.75, "it0winrate511": 0.0}, {"version": "6.1.1", "it4winrate511": 0.5555555555555556, "it3winrate511": 0.23529411764705882, "it1tot511": 2, "it0wins511": 1, "it3wins511": 4, "it5wins511": 5, "it4wins511": 10, "champion_id": 245, "it3tot511": 17, "it2wins511": 3, "it1winrate511": 0.0, "it4tot511": 18, "it5tot511": 18, "it0tot511": 3, "it2tot511": 4, "name": "Ekko", "matchversion": "5.11", "region": "KR", "it2winrate511": 0.75, "it1wins511": 0, "it5winrate511": 0.2777777777777778, "it0winrate511": 0.3333333333333333}, {"version": "6.1.1", "it4winrate511": 0.45454545454545453, "it3winrate511": 0.5555555555555556, "it1tot511": 1, "it0wins511": 1, "it3wins511": 5, "it5wins511": 4, "it4wins511": 5, "champion_id": 111, "it3tot511": 9, "it2wins511": 1, "it1winrate511": 0.0, "it4tot511": 11, "it5tot511": 8, "it0tot511": 1, "it2tot511": 2, "name": "Nautilus", "matchversion": "5.11", "region": "KR", "it2winrate511": 0.5, "it1wins511": 0, "it5winrate511": 0.5, "it0winrate511": 1.0}, {"version": "6.1.1", "it4winrate511": 0.4, "it3winrate511": 0.0, "it1tot511": 3, "it0wins511": 2, "it3wins511": 0, "it5wins511": 4, "it4wins511": 4, "champion_id": 81, "it3tot511": 4, "it2wins511": 1, "it1winrate511": 0.3333333333333333, "it4tot511": 10, "it5tot511": 9, "it0tot511": 2, "it2tot511": 4, "name": "Ezreal", "matchversion": "5.11", "region": "KR", "it2winrate511": 0.25, "it1wins511": 1, "it5winrate511": 0.4444444444444444, "it0winrate511": 1.0}]