[{"version": "6.1.1", "it4winrate511": 0.5714285714285714, "it3winrate511": 0.5757575757575758, "it1tot511": 44, "it0wins511": 2, "it3wins511": 38, "it5wins511": 10, "it4wins511": 24, "champion_id": 19, "it3tot511": 66, "it2wins511": 30, "it1winrate511": 0.5681818181818182, "it4tot511": 42, "it5tot511": 15, "it0tot511": 3, "it2tot511": 51, "name": "Warwick", "matchversion": "5.11", "region": "NA", "it2winrate511": 0.5882352941176471, "it1wins511": 25, "it5winrate511": 0.6666666666666666, "it0winrate511": 0.6666666666666666}, {"version": "6.1.1", "it4winrate511": 0.0, "it3winrate511": 0.6, "it1tot511": 0, "it0wins511": 1, "it3wins511": 3, "it5wins511": 1, "it4wins511": 0, "champion_id": 39, "it3tot511": 5, "it2wins511": 4, "it1winrate511": 0, "it4tot511": 1, "it5tot511": 1, "it0tot511": 1, "it2tot511": 7, "name": "Irelia", "matchversion": "5.11", "region": "NA", "it2winrate511": 0.5714285714285714, "it1wins511": 0, "it5winrate511": 1.0, "it0winrate511": 1.0}, {"version": "6.1.1", "it4winrate511": 0.75, "it3winrate511": 0.375, "it1tot511": 5, "it0wins511": 1, "it3wins511": 3, "it5wins511": 1, "it4wins511": 6, "champion_id": 31, "it3tot511": 8, "it2wins511": 6, "it1winrate511": 0.0, "it4tot511": 8, "it5tot511": 3, "it0tot511": 3, "it2tot511": 10, "name": "Cho'Gath", "matchversion": "5.11", "region": "NA", "it2winrate511": 0.6, "it1wins511": 0, "it5winrate511": 0.3333333333333333, "it0winrate511": 0.3333333333333333}, {"version": "6.1.1", "it4winrate511": 0.625, "it3winrate511": 0.7777777777777778, "it1tot511": 11, "it0wins511": 0, "it3wins511": 21, "it5wins511": 5, "it4wins511": 10, "champion_id": 77, "it3tot511": 27, "it2wins511": 8, "it1winrate511": 0.5454545454545454, "it4tot511": 16, "it5tot511": 9, "it0tot511": 0, "it2tot511": 14, "name": "Udyr", "matchversion": "5.11", "region": "NA", "it2winrate511": 0.5714285714285714, "it1wins511": 6, "it5winrate511": 0.5555555555555556, "it0winrate511": 0}, {"version": "6.1.1", "it4winrate511": 0.6, "it3winrate511": 0.3, "it1tot511": 2, "it0wins511": 1, "it3wins511": 3, "it5wins511": 4, "it4wins511": 3, "champion_id": 72, "it3tot511": 10, "it2wins511": 0, "it1winrate511": 0.5, "it4tot511": 5, "it5tot511": 4, "it0tot511": 1, "it2tot511": 1, "name": "Skarner", "matchversion": "5.11", "region": "NA", "it2winrate511": 0.0, "it1wins511": 1, "it5winrate511": 1.0, "it0winrate511": 1.0}, {"version": "6.1.1", "it4winrate511": 0.4, "it3winrate511": 0.8, "it1tot511": 1, "it0wins511": 1, "it3wins511": 4, "it5wins511": 1, "it4wins511": 2, "champion_id": 17, "it3tot511": 5, "it2wins511": 5, "it1winrate511": 1.0, "it4tot511": 5, "it5tot511": 2, "it0tot511": 2, "it2tot511": 10, "name": "Teemo", "matchversion": "5.11", "region": "NA", "it2winrate511": 0.5, "it1wins511": 1, "it5winrate511": 0.5, "it0winrate511": 0.5}]