[{"it3wins511": 24, "it4tot511": 39, "matchversion": "5.11", "name": "Nidalee", "it5wins511": 14, "it4wins511": 19, "region": "LAS", "champion_id": 76, "it3tot511": 52, "it2tot511": 55, "it2wins511": 28, "it0tot511": 26, "version": "6.1.1", "it1tot511": 93, "it1wins511": 44, "it0wins511": 8, "it5tot511": 20}, {"it3wins511": 11, "it4tot511": 9, "matchversion": "5.11", "name": "Brand", "it5wins511": 3, "it4wins511": 5, "region": "LAS", "champion_id": 63, "it3tot511": 19, "it2tot511": 16, "it2wins511": 10, "it0tot511": 12, "version": "6.1.1", "it1tot511": 13, "it1wins511": 4, "it0wins511": 4, "it5tot511": 7}, {"it3wins511": 33, "it4tot511": 51, "matchversion": "5.11", "name": "Xerath", "it5wins511": 9, "it4wins511": 31, "region": "LAS", "champion_id": 101, "it3tot511": 66, "it2tot511": 84, "it2wins511": 32, "it0tot511": 52, "version": "6.1.1", "it1tot511": 95, "it1wins511": 42, "it0wins511": 22, "it5tot511": 16}, {"it3wins511": 5, "it4tot511": 8, "matchversion": "5.11", "name": "Orianna", "it5wins511": 2, "it4wins511": 4, "region": "LAS", "champion_id": 61, "it3tot511": 7, "it2tot511": 10, "it2wins511": 6, "it0tot511": 8, "version": "6.1.1", "it1tot511": 13, "it1wins511": 6, "it0wins511": 5, "it5tot511": 3}, {"it3wins511": 92, "it4tot511": 110, "matchversion": "5.11", "name": "Lux", "it5wins511": 38, "it4wins511": 68, "region": "LAS", "champion_id": 99, "it3tot511": 158, "it2tot511": 146, "it2wins511": 82, "it0tot511": 94, "version": "6.1.1", "it1tot511": 176, "it1wins511": 86, "it0wins511": 44, "it5tot511": 61}, {"it3wins511": 12, "it4tot511": 31, "matchversion": "5.11", "name": "Fizz", "it5wins511": 7, "it4wins511": 18, "region": "LAS", "champion_id": 105, "it3tot511": 22, "it2tot511": 21, "it2wins511": 10, "it0tot511": 6, "version": "6.1.1", "it1tot511": 24, "it1wins511": 15, "it0wins511": 4, "it5tot511": 14}, {"it3wins511": 14, "it4tot511": 12, "matchversion": "5.11", "name": "Sona", "it5wins511": 0, "it4wins511": 5, "region": "LAS", "champion_id": 37, "it3tot511": 20, "it2tot511": 9, "it2wins511": 5, "it0tot511": 4, "version": "6.1.1", "it1tot511": 13, "it1wins511": 4, "it0wins511": 2, "it5tot511": 1}, {"it3wins511": 4, "it4tot511": 5, "matchversion": "5.11", "name": "Ziggs", "it5wins511": 4, "it4wins511": 2, "region": "LAS", "champion_id": 115, "it3tot511": 13, "it2tot511": 18, "it2wins511": 7, "it0tot511": 12, "version": "6.1.1", "it1tot511": 17, "it1wins511": 8, "it0wins511": 5, "it5tot511": 5}, {"it3wins511": 7, "it4tot511": 6, "matchversion": "5.11", "name": "Syndra", "it5wins511": 4, "it4wins511": 4, "region": "LAS", "champion_id": 134, "it3tot511": 11, "it2tot511": 13, "it2wins511": 4, "it0tot511": 11, "version": "6.1.1", "it1tot511": 11, "it1wins511": 6, "it0wins511": 6, "it5tot511": 5}, {"it3wins511": 11, "it4tot511": 22, "matchversion": "5.11", "name": "Karma", "it5wins511": 10, "it4wins511": 11, "region": "LAS", "champion_id": 43, "it3tot511": 23, "it2tot511": 31, "it2wins511": 16, "it0tot511": 11, "version": "6.1.1", "it1tot511": 17, "it1wins511": 7, "it0wins511": 7, "it5tot511": 13}, {"it3wins511": 28, "it4tot511": 42, "matchversion": "5.11", "name": "Annie", "it5wins511": 14, "it4wins511": 24, "region": "LAS", "champion_id": 1, "it3tot511": 43, "it2tot511": 36, "it2wins511": 20, "it0tot511": 22, "version": "6.1.1", "it1tot511": 45, "it1wins511": 19, "it0wins511": 11, "it5tot511": 24}, {"it3wins511": 10, "it4tot511": 18, "matchversion": "5.11", "name": "Twisted Fate", "it5wins511": 5, "it4wins511": 8, "region": "LAS", "champion_id": 4, "it3tot511": 21, "it2tot511": 13, "it2wins511": 5, "it0tot511": 9, "version": "6.1.1", "it1tot511": 11, "it1wins511": 2, "it0wins511": 7, "it5tot511": 7}, {"it3wins511": 26, "it4tot511": 61, "matchversion": "5.11", "name": "Morgana", "it5wins511": 19, "it4wins511": 30, "region": "LAS", "champion_id": 25, "it3tot511": 56, "it2tot511": 41, "it2wins511": 20, "it0tot511": 26, "version": "6.1.1", "it1tot511": 33, "it1wins511": 16, "it0wins511": 11, "it5tot511": 23}, {"it3wins511": 21, "it4tot511": 43, "matchversion": "5.11", "name": "Azir", "it5wins511": 15, "it4wins511": 23, "region": "LAS", "champion_id": 268, "it3tot511": 60, "it2tot511": 73, "it2wins511": 32, "it0tot511": 42, "version": "6.1.1", "it1tot511": 99, "it1wins511": 53, "it0wins511": 22, "it5tot511": 23}, {"it3wins511": 42, "it4tot511": 55, "matchversion": "5.11", "name": "Teemo", "it5wins511": 25, "it4wins511": 31, "region": "LAS", "champion_id": 17, "it3tot511": 77, "it2tot511": 79, "it2wins511": 47, "it0tot511": 54, "version": "6.1.1", "it1tot511": 81, "it1wins511": 45, "it0wins511": 27, "it5tot511": 41}, {"it3wins511": 25, "it4tot511": 25, "matchversion": "5.11", "name": "Heimerdinger", "it5wins511": 7, "it4wins511": 14, "region": "LAS", "champion_id": 74, "it3tot511": 45, "it2tot511": 61, "it2wins511": 39, "it0tot511": 27, "version": "6.1.1", "it1tot511": 49, "it1wins511": 32, "it0wins511": 21, "it5tot511": 15}, {"it3wins511": 12, "it4tot511": 11, "matchversion": "5.11", "name": "Vel'Koz", "it5wins511": 6, "it4wins511": 6, "region": "LAS", "champion_id": 161, "it3tot511": 18, "it2tot511": 24, "it2wins511": 13, "it0tot511": 12, "version": "6.1.1", "it1tot511": 20, "it1wins511": 10, "it0wins511": 9, "it5tot511": 9}, {"it3wins511": 114, "it4tot511": 238, "matchversion": "5.11", "name": "Ekko", "it5wins511": 58, "it4wins511": 148, "region": "LAS", "champion_id": 245, "it3tot511": 223, "it2tot511": 238, "it2wins511": 130, "it0tot511": 131, "version": "6.1.1", "it1tot511": 205, "it1wins511": 110, "it0wins511": 64, "it5tot511": 97}, {"it3wins511": 3, "it4tot511": 10, "matchversion": "5.11", "name": "Malzahar", "it5wins511": 5, "it4wins511": 7, "region": "LAS", "champion_id": 90, "it3tot511": 11, "it2tot511": 8, "it2wins511": 4, "it0tot511": 9, "version": "6.1.1", "it1tot511": 7, "it1wins511": 5, "it0wins511": 5, "it5tot511": 7}, {"it3wins511": 10, "it4tot511": 7, "matchversion": "5.11", "name": "Lissandra", "it5wins511": 4, "it4wins511": 2, "region": "LAS", "champion_id": 127, "it3tot511": 20, "it2tot511": 15, "it2wins511": 6, "it0tot511": 5, "version": "6.1.1", "it1tot511": 15, "it1wins511": 6, "it0wins511": 3, "it5tot511": 6}, {"it3wins511": 13, "it4tot511": 15, "matchversion": "5.11", "name": "Veigar", "it5wins511": 4, "it4wins511": 7, "region": "LAS", "champion_id": 45, "it3tot511": 25, "it2tot511": 22, "it2wins511": 7, "it0tot511": 19, "version": "6.1.1", "it1tot511": 36, "it1wins511": 22, "it0wins511": 13, "it5tot511": 7}, {"it3wins511": 15, "it4tot511": 26, "matchversion": "5.11", "name": "Lulu", "it5wins511": 6, "it4wins511": 10, "region": "LAS", "champion_id": 117, "it3tot511": 23, "it2tot511": 23, "it2wins511": 9, "it0tot511": 17, "version": "6.1.1", "it1tot511": 25, "it1wins511": 16, "it0wins511": 8, "it5tot511": 9}, {"it3wins511": 54, "it4tot511": 65, "matchversion": "5.11", "name": "Ahri", "it5wins511": 16, "it4wins511": 31, "region": "LAS", "champion_id": 103, "it3tot511": 99, "it2tot511": 106, "it2wins511": 61, "it0tot511": 57, "version": "6.1.1", "it1tot511": 162, "it1wins511": 93, "it0wins511": 30, "it5tot511": 29}, {"it3wins511": 44, "it4tot511": 70, "matchversion": "5.11", "name": "LeBlanc", "it5wins511": 21, "it4wins511": 31, "region": "LAS", "champion_id": 7, "it3tot511": 99, "it2tot511": 109, "it2wins511": 54, "it0tot511": 65, "version": "6.1.1", "it1tot511": 178, "it1wins511": 79, "it0wins511": 24, "it5tot511": 37}, {"it3wins511": 1, "it4tot511": 3, "matchversion": "5.11", "name": "Ezreal", "it5wins511": 0, "it4wins511": 0, "region": "LAS", "champion_id": 81, "it3tot511": 2, "it2tot511": 7, "it2wins511": 3, "it0tot511": 1, "version": "6.1.1", "it1tot511": 5, "it1wins511": 4, "it0wins511": 1, "it5tot511": 0}]