[{"version": "6.1.1", "it4winrate511": 1.0, "it3winrate511": 0.8333333333333334, "it1tot511": 117, "it0wins511": 61, "it3wins511": 10, "it5wins511": 4, "it4wins511": 4, "champion_id": 24, "it3tot511": 12, "it2wins511": 44, "it1winrate511": 0.5042735042735043, "it4tot511": 4, "it5tot511": 4, "it0tot511": 99, "it2tot511": 58, "name": "Jax", "matchversion": "5.11", "it5winrate511": 1.0, "it2winrate511": 0.7586206896551724, "it1wins511": 59, "it0winrate511": 0.6161616161616161}, {"version": "6.1.1", "it4winrate511": 0.0, "it3winrate511": 0, "it1tot511": 9, "it0wins511": 1, "it3wins511": 0, "it5wins511": 0, "it4wins511": 0, "champion_id": 19, "it3tot511": 0, "it2wins511": 4, "it1winrate511": 1.0, "it4tot511": 1, "it5tot511": 0, "it0tot511": 5, "it2tot511": 4, "name": "Warwick", "matchversion": "5.11", "it5winrate511": 0, "it2winrate511": 1.0, "it1wins511": 9, "it0winrate511": 0.2}, {"version": "6.1.1", "it4winrate511": 0, "it3winrate511": 0, "it1tot511": 3, "it0wins511": 6, "it3wins511": 0, "it5wins511": 0, "it4wins511": 0, "champion_id": 76, "it3tot511": 0, "it2wins511": 1, "it1winrate511": 0.3333333333333333, "it4tot511": 0, "it5tot511": 0, "it0tot511": 8, "it2tot511": 4, "name": "Nidalee", "matchversion": "5.11", "it5winrate511": 0, "it2winrate511": 0.25, "it1wins511": 1, "it0winrate511": 0.75}, {"version": "6.1.1", "it4winrate511": 0.3333333333333333, "it3winrate511": 0.75, "it1tot511": 50, "it0wins511": 23, "it3wins511": 3, "it5wins511": 0, "it4wins511": 1, "champion_id": 78, "it3tot511": 4, "it2wins511": 13, "it1winrate511": 0.54, "it4tot511": 3, "it5tot511": 1, "it0tot511": 38, "it2tot511": 22, "name": "Poppy", "matchversion": "5.11", "it5winrate511": 0.0, "it2winrate511": 0.5909090909090909, "it1wins511": 27, "it0winrate511": 0.6052631578947368}, {"version": "6.1.1", "it4winrate511": 1.0, "it3winrate511": 1.0, "it1tot511": 8, "it0wins511": 4, "it3wins511": 1, "it5wins511": 1, "it4wins511": 1, "champion_id": 105, "it3tot511": 1, "it2wins511": 6, "it1winrate511": 0.375, "it4tot511": 1, "it5tot511": 1, "it0tot511": 8, "it2tot511": 9, "name": "Fizz", "matchversion": "5.11", "it5winrate511": 1.0, "it2winrate511": 0.6666666666666666, "it1wins511": 3, "it0winrate511": 0.5}, {"version": "6.1.1", "it4winrate511": 0.0, "it3winrate511": 1.0, "it1tot511": 18, "it0wins511": 9, "it3wins511": 1, "it5wins511": 2, "it4wins511": 0, "champion_id": 10, "it3tot511": 1, "it2wins511": 6, "it1winrate511": 0.6111111111111112, "it4tot511": 1, "it5tot511": 2, "it0tot511": 24, "it2tot511": 8, "name": "Kayle", "matchversion": "5.11", "it5winrate511": 1.0, "it2winrate511": 0.75, "it1wins511": 11, "it0winrate511": 0.375}, {"version": "6.1.1", "it4winrate511": 0.5555555555555556, "it3winrate511": 0.5116279069767442, "it1tot511": 1388, "it0wins511": 957, "it3wins511": 44, "it5wins511": 19, "it4wins511": 15, "champion_id": 84, "it3tot511": 86, "it2wins511": 307, "it1winrate511": 0.5172910662824207, "it4tot511": 27, "it5tot511": 35, "it0tot511": 1884, "it2tot511": 579, "name": "Akali", "matchversion": "5.11", "it5winrate511": 0.5428571428571428, "it2winrate511": 0.5302245250431779, "it1wins511": 718, "it0winrate511": 0.5079617834394905}, {"version": "6.1.1", "it4winrate511": 0, "it3winrate511": 0.5, "it1tot511": 18, "it0wins511": 2, "it3wins511": 1, "it5wins511": 1, "it4wins511": 0, "champion_id": 85, "it3tot511": 2, "it2wins511": 1, "it1winrate511": 0.5555555555555556, "it4tot511": 0, "it5tot511": 1, "it0tot511": 7, "it2tot511": 6, "name": "Kennen", "matchversion": "5.11", "it5winrate511": 1.0, "it2winrate511": 0.16666666666666666, "it1wins511": 10, "it0winrate511": 0.2857142857142857}, {"version": "6.1.1", "it4winrate511": 1.0, "it3winrate511": 0.5, "it1tot511": 10, "it0wins511": 1, "it3wins511": 1, "it5wins511": 0, "it4wins511": 1, "champion_id": 4, "it3tot511": 2, "it2wins511": 0, "it1winrate511": 0.5, "it4tot511": 1, "it5tot511": 1, "it0tot511": 2, "it2tot511": 1, "name": "Twisted Fate", "matchversion": "5.11", "it5winrate511": 0.0, "it2winrate511": 0.0, "it1wins511": 5, "it0winrate511": 0.5}, {"version": "6.1.1", "it4winrate511": 0, "it3winrate511": 0, "it1tot511": 8, "it0wins511": 0, "it3wins511": 0, "it5wins511": 0, "it4wins511": 0, "champion_id": 31, "it3tot511": 0, "it2wins511": 0, "it1winrate511": 0.375, "it4tot511": 0, "it5tot511": 0, "it0tot511": 0, "it2tot511": 0, "name": "Cho'Gath", "matchversion": "5.11", "it5winrate511": 0, "it2winrate511": 0, "it1wins511": 3, "it0winrate511": 0}, {"version": "6.1.1", "it4winrate511": 0.0, "it3winrate511": 1.0, "it1tot511": 18, "it0wins511": 9, "it3wins511": 1, "it5wins511": 1, "it4wins511": 0, "champion_id": 17, "it3tot511": 1, "it2wins511": 5, "it1winrate511": 0.5555555555555556, "it4tot511": 1, "it5tot511": 2, "it0tot511": 19, "it2tot511": 8, "name": "Teemo", "matchversion": "5.11", "it5winrate511": 0.5, "it2winrate511": 0.625, "it1wins511": 10, "it0winrate511": 0.47368421052631576}, {"version": "6.1.1", "it4winrate511": 0.0, "it3winrate511": 0.0, "it1tot511": 17, "it0wins511": 5, "it3wins511": 0, "it5wins511": 0, "it4wins511": 0, "champion_id": 131, "it3tot511": 1, "it2wins511": 4, "it1winrate511": 0.7058823529411765, "it4tot511": 1, "it5tot511": 1, "it0tot511": 8, "it2tot511": 8, "name": "Diana", "matchversion": "5.11", "it5winrate511": 0.0, "it2winrate511": 0.5, "it1wins511": 12, "it0winrate511": 0.625}, {"version": "6.1.1", "it4winrate511": 0.5555555555555556, "it3winrate511": 0.47058823529411764, "it1tot511": 168, "it0wins511": 89, "it3wins511": 8, "it5wins511": 5, "it4wins511": 5, "champion_id": 55, "it3tot511": 17, "it2wins511": 47, "it1winrate511": 0.5238095238095238, "it4tot511": 9, "it5tot511": 8, "it0tot511": 165, "it2tot511": 83, "name": "Katarina", "matchversion": "5.11", "it5winrate511": 0.625, "it2winrate511": 0.5662650602409639, "it1wins511": 88, "it0winrate511": 0.5393939393939394}, {"version": "6.1.1", "it4winrate511": 0.6666666666666666, "it3winrate511": 0.4, "it1tot511": 43, "it0wins511": 29, "it3wins511": 2, "it5wins511": 3, "it4wins511": 2, "champion_id": 245, "it3tot511": 5, "it2wins511": 8, "it1winrate511": 0.627906976744186, "it4tot511": 3, "it5tot511": 4, "it0tot511": 46, "it2tot511": 16, "name": "Ekko", "matchversion": "5.11", "it5winrate511": 0.75, "it2winrate511": 0.5, "it1wins511": 27, "it0winrate511": 0.6304347826086957}, {"version": "6.1.1", "it4winrate511": 0.0, "it3winrate511": 0.5, "it1tot511": 98, "it0wins511": 57, "it3wins511": 2, "it5wins511": 0, "it4wins511": 0, "champion_id": 82, "it3tot511": 4, "it2wins511": 28, "it1winrate511": 0.5, "it4tot511": 1, "it5tot511": 1, "it0tot511": 113, "it2tot511": 42, "name": "Mordekaiser", "matchversion": "5.11", "it5winrate511": 0.0, "it2winrate511": 0.6666666666666666, "it1wins511": 49, "it0winrate511": 0.504424778761062}, {"version": "6.1.1", "it4winrate511": 0, "it3winrate511": 0, "it1tot511": 3, "it0wins511": 3, "it3wins511": 0, "it5wins511": 0, "it4wins511": 0, "champion_id": 5, "it3tot511": 0, "it2wins511": 3, "it1winrate511": 0.3333333333333333, "it4tot511": 0, "it5tot511": 0, "it0tot511": 9, "it2tot511": 3, "name": "Xin Zhao", "matchversion": "5.11", "it5winrate511": 0, "it2winrate511": 1.0, "it1wins511": 1, "it0winrate511": 0.3333333333333333}, {"version": "6.1.1", "it4winrate511": 0, "it3winrate511": 0.0, "it1tot511": 12, "it0wins511": 6, "it3wins511": 0, "it5wins511": 0, "it4wins511": 0, "champion_id": 8, "it3tot511": 1, "it2wins511": 3, "it1winrate511": 0.4166666666666667, "it4tot511": 0, "it5tot511": 0, "it0tot511": 12, "it2tot511": 6, "name": "Vladimir", "matchversion": "5.11", "it5winrate511": 0, "it2winrate511": 0.5, "it1wins511": 5, "it0winrate511": 0.5}, {"version": "6.1.1", "it4winrate511": 0.8333333333333334, "it3winrate511": 0.6, "it1tot511": 181, "it0wins511": 92, "it3wins511": 6, "it5wins511": 2, "it4wins511": 5, "champion_id": 28, "it3tot511": 10, "it2wins511": 60, "it1winrate511": 0.569060773480663, "it4tot511": 6, "it5tot511": 6, "it0tot511": 144, "it2tot511": 99, "name": "Evelynn", "matchversion": "5.11", "it5winrate511": 0.3333333333333333, "it2winrate511": 0.6060606060606061, "it1wins511": 103, "it0winrate511": 0.6388888888888888}, {"version": "6.1.1", "it4winrate511": 0.0, "it3winrate511": 0.0, "it1tot511": 10, "it0wins511": 5, "it3wins511": 0, "it5wins511": 0, "it4wins511": 0, "champion_id": 81, "it3tot511": 1, "it2wins511": 3, "it1winrate511": 0.7, "it4tot511": 1, "it5tot511": 0, "it0tot511": 9, "it2tot511": 6, "name": "Ezreal", "matchversion": "5.11", "it5winrate511": 0, "it2winrate511": 0.5, "it1wins511": 7, "it0winrate511": 0.5555555555555556}]