[{"version": "6.1.1", "it4winrate511": 0, "it3winrate511": 0, "it1tot511": 5, "it0wins511": 7, "it3wins511": 0, "it5wins511": 0, "it4wins511": 0, "champion_id": 35, "it3tot511": 0, "it2wins511": 0, "it1winrate511": 0.2, "it4tot511": 0, "it5tot511": 0, "it0tot511": 16, "it2tot511": 1, "name": "Shaco", "matchversion": "5.11", "it5winrate511": 0, "it2winrate511": 0.0, "it1wins511": 1, "it0winrate511": 0.4375}, {"version": "6.1.1", "it4winrate511": 0.5, "it3winrate511": 0.0, "it1tot511": 38, "it0wins511": 67, "it3wins511": 0, "it5wins511": 0, "it4wins511": 1, "champion_id": 76, "it3tot511": 3, "it2wins511": 10, "it1winrate511": 0.47368421052631576, "it4tot511": 2, "it5tot511": 0, "it0tot511": 143, "it2tot511": 22, "name": "Nidalee", "matchversion": "5.11", "it5winrate511": 0, "it2winrate511": 0.45454545454545453, "it1wins511": 18, "it0winrate511": 0.46853146853146854}, {"version": "6.1.1", "it4winrate511": 0.0, "it3winrate511": 0.47619047619047616, "it1tot511": 135, "it0wins511": 239, "it3wins511": 10, "it5wins511": 2, "it4wins511": 0, "champion_id": 143, "it3tot511": 21, "it2wins511": 53, "it1winrate511": 0.5777777777777777, "it4tot511": 7, "it5tot511": 4, "it0tot511": 438, "it2tot511": 100, "name": "Zyra", "matchversion": "5.11", "it5winrate511": 0.5, "it2winrate511": 0.53, "it1wins511": 78, "it0winrate511": 0.545662100456621}, {"version": "6.1.1", "it4winrate511": 0, "it3winrate511": 0.5, "it1tot511": 37, "it0wins511": 67, "it3wins511": 1, "it5wins511": 0, "it4wins511": 0, "champion_id": 63, "it3tot511": 2, "it2wins511": 14, "it1winrate511": 0.5135135135135135, "it4tot511": 0, "it5tot511": 0, "it0tot511": 122, "it2tot511": 32, "name": "Brand", "matchversion": "5.11", "it5winrate511": 0, "it2winrate511": 0.4375, "it1wins511": 19, "it0winrate511": 0.5491803278688525}, {"version": "6.1.1", "it4winrate511": 0, "it3winrate511": 0.0, "it1tot511": 10, "it0wins511": 9, "it3wins511": 0, "it5wins511": 1, "it4wins511": 0, "champion_id": 34, "it3tot511": 2, "it2wins511": 7, "it1winrate511": 0.4, "it4tot511": 0, "it5tot511": 2, "it0tot511": 23, "it2tot511": 7, "name": "Anivia", "matchversion": "5.11", "it5winrate511": 0.5, "it2winrate511": 1.0, "it1wins511": 4, "it0winrate511": 0.391304347826087}, {"version": "6.1.1", "it4winrate511": 0.0, "it3winrate511": 0.2, "it1tot511": 7, "it0wins511": 21, "it3wins511": 1, "it5wins511": 0, "it4wins511": 0, "champion_id": 53, "it3tot511": 5, "it2wins511": 7, "it1winrate511": 0.5714285714285714, "it4tot511": 1, "it5tot511": 0, "it0tot511": 44, "it2tot511": 11, "name": "Blitzcrank", "matchversion": "5.11", "it5winrate511": 0, "it2winrate511": 0.6363636363636364, "it1wins511": 4, "it0winrate511": 0.4772727272727273}, {"version": "6.1.1", "it4winrate511": 0, "it3winrate511": 1.0, "it1tot511": 16, "it0wins511": 13, "it3wins511": 1, "it5wins511": 0, "it4wins511": 0, "champion_id": 101, "it3tot511": 1, "it2wins511": 4, "it1winrate511": 0.5625, "it4tot511": 0, "it5tot511": 0, "it0tot511": 36, "it2tot511": 8, "name": "Xerath", "matchversion": "5.11", "it5winrate511": 0, "it2winrate511": 0.5, "it1wins511": 9, "it0winrate511": 0.3611111111111111}, {"version": "6.1.1", "it4winrate511": 0, "it3winrate511": 0.5, "it1tot511": 13, "it0wins511": 12, "it3wins511": 1, "it5wins511": 0, "it4wins511": 0, "champion_id": 61, "it3tot511": 2, "it2wins511": 4, "it1winrate511": 0.5384615384615384, "it4tot511": 0, "it5tot511": 0, "it0tot511": 28, "it2tot511": 11, "name": "Orianna", "matchversion": "5.11", "it5winrate511": 0, "it2winrate511": 0.36363636363636365, "it1wins511": 7, "it0winrate511": 0.42857142857142855}, {"version": "6.1.1", "it4winrate511": 0, "it3winrate511": 0.0, "it1tot511": 20, "it0wins511": 47, "it3wins511": 0, "it5wins511": 0, "it4wins511": 0, "champion_id": 54, "it3tot511": 2, "it2wins511": 7, "it1winrate511": 0.55, "it4tot511": 0, "it5tot511": 0, "it0tot511": 82, "it2tot511": 13, "name": "Malphite", "matchversion": "5.11", "it5winrate511": 0, "it2winrate511": 0.5384615384615384, "it1wins511": 11, "it0winrate511": 0.573170731707317}, {"version": "6.1.1", "it4winrate511": 0, "it3winrate511": 0.0, "it1tot511": 12, "it0wins511": 16, "it3wins511": 0, "it5wins511": 0, "it4wins511": 0, "champion_id": 20, "it3tot511": 1, "it2wins511": 3, "it1winrate511": 0.6666666666666666, "it4tot511": 0, "it5tot511": 0, "it0tot511": 48, "it2tot511": 5, "name": "Nunu", "matchversion": "5.11", "it5winrate511": 0, "it2winrate511": 0.6, "it1wins511": 8, "it0winrate511": 0.3333333333333333}, {"version": "6.1.1", "it4winrate511": 0.38461538461538464, "it3winrate511": 0.6, "it1tot511": 190, "it0wins511": 298, "it3wins511": 12, "it5wins511": 3, "it4wins511": 5, "champion_id": 99, "it3tot511": 20, "it2wins511": 70, "it1winrate511": 0.48947368421052634, "it4tot511": 13, "it5tot511": 5, "it0tot511": 580, "it2tot511": 131, "name": "Lux", "matchversion": "5.11", "it5winrate511": 0.6, "it2winrate511": 0.5343511450381679, "it1wins511": 93, "it0winrate511": 0.5137931034482759}, {"version": "6.1.1", "it4winrate511": 0.5161290322580645, "it3winrate511": 0.5, "it1tot511": 813, "it0wins511": 1526, "it3wins511": 37, "it5wins511": 12, "it4wins511": 16, "champion_id": 37, "it3tot511": 74, "it2wins511": 248, "it1winrate511": 0.5399753997539976, "it4tot511": 31, "it5tot511": 22, "it0tot511": 2725, "it2tot511": 472, "name": "Sona", "matchversion": "5.11", "it5winrate511": 0.5454545454545454, "it2winrate511": 0.5254237288135594, "it1wins511": 439, "it0winrate511": 0.56}, {"version": "6.1.1", "it4winrate511": 0, "it3winrate511": 0.0, "it1tot511": 5, "it0wins511": 5, "it3wins511": 0, "it5wins511": 0, "it4wins511": 0, "champion_id": 69, "it3tot511": 1, "it2wins511": 2, "it1winrate511": 0.4, "it4tot511": 0, "it5tot511": 0, "it0tot511": 12, "it2tot511": 6, "name": "Cassiopeia", "matchversion": "5.11", "it5winrate511": 0, "it2winrate511": 0.3333333333333333, "it1wins511": 2, "it0winrate511": 0.4166666666666667}, {"version": "6.1.1", "it4winrate511": 0, "it3winrate511": 1.0, "it1tot511": 1, "it0wins511": 4, "it3wins511": 1, "it5wins511": 0, "it4wins511": 0, "champion_id": 57, "it3tot511": 1, "it2wins511": 1, "it1winrate511": 1.0, "it4tot511": 0, "it5tot511": 0, "it0tot511": 8, "it2tot511": 2, "name": "Maokai", "matchversion": "5.11", "it5winrate511": 0, "it2winrate511": 0.5, "it1wins511": 1, "it0winrate511": 0.5}, {"version": "6.1.1", "it4winrate511": 0, "it3winrate511": 0, "it1tot511": 2, "it0wins511": 9, "it3wins511": 0, "it5wins511": 0, "it4wins511": 0, "champion_id": 412, "it3tot511": 0, "it2wins511": 1, "it1winrate511": 0.5, "it4tot511": 0, "it5tot511": 0, "it0tot511": 18, "it2tot511": 1, "name": "Thresh", "matchversion": "5.11", "it5winrate511": 0, "it2winrate511": 1.0, "it1wins511": 1, "it0winrate511": 0.5}, {"version": "6.1.1", "it4winrate511": 0, "it3winrate511": 0.0, "it1tot511": 17, "it0wins511": 34, "it3wins511": 0, "it5wins511": 0, "it4wins511": 0, "champion_id": 10, "it3tot511": 2, "it2wins511": 5, "it1winrate511": 0.6470588235294118, "it4tot511": 0, "it5tot511": 0, "it0tot511": 63, "it2tot511": 9, "name": "Kayle", "matchversion": "5.11", "it5winrate511": 0, "it2winrate511": 0.5555555555555556, "it1wins511": 11, "it0winrate511": 0.5396825396825397}, {"version": "6.1.1", "it4winrate511": 0, "it3winrate511": 0.0, "it1tot511": 4, "it0wins511": 7, "it3wins511": 0, "it5wins511": 1, "it4wins511": 0, "champion_id": 115, "it3tot511": 1, "it2wins511": 2, "it1winrate511": 0.0, "it4tot511": 0, "it5tot511": 1, "it0tot511": 13, "it2tot511": 4, "name": "Ziggs", "matchversion": "5.11", "it5winrate511": 1.0, "it2winrate511": 0.5, "it1wins511": 0, "it0winrate511": 0.5384615384615384}, {"version": "6.1.1", "it4winrate511": 0, "it3winrate511": 0, "it1tot511": 6, "it0wins511": 6, "it3wins511": 0, "it5wins511": 1, "it4wins511": 0, "champion_id": 134, "it3tot511": 0, "it2wins511": 1, "it1winrate511": 0.5, "it4tot511": 0, "it5tot511": 2, "it0tot511": 15, "it2tot511": 2, "name": "Syndra", "matchversion": "5.11", "it5winrate511": 0.5, "it2winrate511": 0.5, "it1wins511": 3, "it0winrate511": 0.4}, {"version": "6.1.1", "it4winrate511": 0.6666666666666666, "it3winrate511": 0.5588235294117647, "it1tot511": 324, "it0wins511": 391, "it3wins511": 19, "it5wins511": 6, "it4wins511": 6, "champion_id": 43, "it3tot511": 34, "it2wins511": 81, "it1winrate511": 0.5709876543209876, "it4tot511": 9, "it5tot511": 11, "it0tot511": 822, "it2tot511": 155, "name": "Karma", "matchversion": "5.11", "it5winrate511": 0.5454545454545454, "it2winrate511": 0.5225806451612903, "it1wins511": 185, "it0winrate511": 0.47566909975669097}, {"version": "6.1.1", "it4winrate511": 0.5625, "it3winrate511": 0.46153846153846156, "it1tot511": 481, "it0wins511": 604, "it3wins511": 24, "it5wins511": 7, "it4wins511": 9, "champion_id": 1, "it3tot511": 52, "it2wins511": 162, "it1winrate511": 0.5571725571725572, "it4tot511": 16, "it5tot511": 9, "it0tot511": 1204, "it2tot511": 290, "name": "Annie", "matchversion": "5.11", "it5winrate511": 0.7777777777777778, "it2winrate511": 0.5586206896551724, "it1wins511": 268, "it0winrate511": 0.5016611295681063}, {"version": "6.1.1", "it4winrate511": 0.5, "it3winrate511": 1.0, "it1tot511": 3, "it0wins511": 9, "it3wins511": 1, "it5wins511": 0, "it4wins511": 1, "champion_id": 85, "it3tot511": 1, "it2wins511": 5, "it1winrate511": 0.3333333333333333, "it4tot511": 2, "it5tot511": 0, "it0tot511": 24, "it2tot511": 11, "name": "Kennen", "matchversion": "5.11", "it5winrate511": 0, "it2winrate511": 0.45454545454545453, "it1wins511": 1, "it0winrate511": 0.375}, {"version": "6.1.1", "it4winrate511": 0, "it3winrate511": 0, "it1tot511": 5, "it0wins511": 5, "it3wins511": 0, "it5wins511": 0, "it4wins511": 0, "champion_id": 13, "it3tot511": 0, "it2wins511": 1, "it1winrate511": 0.6, "it4tot511": 0, "it5tot511": 0, "it0tot511": 9, "it2tot511": 1, "name": "Ryze", "matchversion": "5.11", "it5winrate511": 0, "it2winrate511": 1.0, "it1wins511": 3, "it0winrate511": 0.5555555555555556}, {"version": "6.1.1", "it4winrate511": 0, "it3winrate511": 0, "it1tot511": 4, "it0wins511": 0, "it3wins511": 0, "it5wins511": 1, "it4wins511": 0, "champion_id": 50, "it3tot511": 0, "it2wins511": 0, "it1winrate511": 0.25, "it4tot511": 0, "it5tot511": 1, "it0tot511": 7, "it2tot511": 0, "name": "Swain", "matchversion": "5.11", "it5winrate511": 1.0, "it2winrate511": 0, "it1wins511": 1, "it0winrate511": 0.0}, {"version": "6.1.1", "it4winrate511": 0.631578947368421, "it3winrate511": 0.3877551020408163, "it1tot511": 290, "it0wins511": 355, "it3wins511": 19, "it5wins511": 11, "it4wins511": 12, "champion_id": 432, "it3tot511": 49, "it2wins511": 83, "it1winrate511": 0.5103448275862069, "it4tot511": 19, "it5tot511": 21, "it0tot511": 730, "it2tot511": 183, "name": "Bard", "matchversion": "5.11", "it5winrate511": 0.5238095238095238, "it2winrate511": 0.453551912568306, "it1wins511": 148, "it0winrate511": 0.4863013698630137}, {"version": "6.1.1", "it4winrate511": 1.0, "it3winrate511": 0, "it1tot511": 9, "it0wins511": 3, "it3wins511": 0, "it5wins511": 0, "it4wins511": 1, "champion_id": 4, "it3tot511": 0, "it2wins511": 2, "it1winrate511": 0.6666666666666666, "it4tot511": 1, "it5tot511": 0, "it0tot511": 5, "it2tot511": 3, "name": "Twisted Fate", "matchversion": "5.11", "it5winrate511": 0, "it2winrate511": 0.6666666666666666, "it1wins511": 6, "it0winrate511": 0.6}, {"version": "6.1.1", "it4winrate511": 0, "it3winrate511": 1.0, "it1tot511": 5, "it0wins511": 9, "it3wins511": 1, "it5wins511": 0, "it4wins511": 0, "champion_id": 31, "it3tot511": 1, "it2wins511": 1, "it1winrate511": 0.2, "it4tot511": 0, "it5tot511": 0, "it0tot511": 21, "it2tot511": 4, "name": "Cho'Gath", "matchversion": "5.11", "it5winrate511": 0, "it2winrate511": 0.25, "it1wins511": 1, "it0winrate511": 0.42857142857142855}, {"version": "6.1.1", "it4winrate511": 0.49333333333333335, "it3winrate511": 0.5534883720930233, "it1tot511": 1910, "it0wins511": 2263, "it3wins511": 119, "it5wins511": 34, "it4wins511": 37, "champion_id": 25, "it3tot511": 215, "it2wins511": 692, "it1winrate511": 0.5450261780104712, "it4tot511": 75, "it5tot511": 65, "it0tot511": 4313, "it2tot511": 1239, "name": "Morgana", "matchversion": "5.11", "it5winrate511": 0.5230769230769231, "it2winrate511": 0.5585149313962873, "it1wins511": 1041, "it0winrate511": 0.524692789241827}, {"version": "6.1.1", "it4winrate511": 0.5, "it3winrate511": 0.5454545454545454, "it1tot511": 65, "it0wins511": 93, "it3wins511": 6, "it5wins511": 0, "it4wins511": 1, "champion_id": 26, "it3tot511": 11, "it2wins511": 17, "it1winrate511": 0.4307692307692308, "it4tot511": 2, "it5tot511": 3, "it0tot511": 204, "it2tot511": 39, "name": "Zilean", "matchversion": "5.11", "it5winrate511": 0.0, "it2winrate511": 0.4358974358974359, "it1wins511": 28, "it0winrate511": 0.45588235294117646}, {"version": "6.1.1", "it4winrate511": 1.0, "it3winrate511": 0.0, "it1tot511": 5, "it0wins511": 4, "it3wins511": 0, "it5wins511": 0, "it4wins511": 1, "champion_id": 268, "it3tot511": 1, "it2wins511": 1, "it1winrate511": 0.8, "it4tot511": 1, "it5tot511": 0, "it0tot511": 11, "it2tot511": 2, "name": "Azir", "matchversion": "5.11", "it5winrate511": 0, "it2winrate511": 0.5, "it1wins511": 4, "it0winrate511": 0.36363636363636365}, {"version": "6.1.1", "it4winrate511": 0, "it3winrate511": 0.6666666666666666, "it1tot511": 24, "it0wins511": 33, "it3wins511": 2, "it5wins511": 0, "it4wins511": 0, "champion_id": 17, "it3tot511": 3, "it2wins511": 10, "it1winrate511": 0.5833333333333334, "it4tot511": 0, "it5tot511": 3, "it0tot511": 53, "it2tot511": 16, "name": "Teemo", "matchversion": "5.11", "it5winrate511": 0.0, "it2winrate511": 0.625, "it1wins511": 14, "it0winrate511": 0.6226415094339622}, {"version": "6.1.1", "it4winrate511": 0, "it3winrate511": 0.5, "it1tot511": 3, "it0wins511": 3, "it3wins511": 1, "it5wins511": 0, "it4wins511": 0, "champion_id": 3, "it3tot511": 2, "it2wins511": 0, "it1winrate511": 0.3333333333333333, "it4tot511": 0, "it5tot511": 0, "it0tot511": 10, "it2tot511": 2, "name": "Galio", "matchversion": "5.11", "it5winrate511": 0, "it2winrate511": 0.0, "it1wins511": 1, "it0winrate511": 0.3}, {"version": "6.1.1", "it4winrate511": 0, "it3winrate511": 0, "it1tot511": 5, "it0wins511": 11, "it3wins511": 0, "it5wins511": 1, "it4wins511": 0, "champion_id": 74, "it3tot511": 0, "it2wins511": 1, "it1winrate511": 0.4, "it4tot511": 0, "it5tot511": 1, "it0tot511": 22, "it2tot511": 2, "name": "Heimerdinger", "matchversion": "5.11", "it5winrate511": 1.0, "it2winrate511": 0.5, "it1wins511": 2, "it0winrate511": 0.5}, {"version": "6.1.1", "it4winrate511": 0.0, "it3winrate511": 0.2857142857142857, "it1tot511": 74, "it0wins511": 95, "it3wins511": 2, "it5wins511": 0, "it4wins511": 0, "champion_id": 161, "it3tot511": 7, "it2wins511": 24, "it1winrate511": 0.581081081081081, "it4tot511": 1, "it5tot511": 0, "it0tot511": 202, "it2tot511": 44, "name": "Vel'Koz", "matchversion": "5.11", "it5winrate511": 0, "it2winrate511": 0.5454545454545454, "it1wins511": 43, "it0winrate511": 0.47029702970297027}, {"version": "6.1.1", "it4winrate511": 0, "it3winrate511": 0.5, "it1tot511": 13, "it0wins511": 9, "it3wins511": 1, "it5wins511": 0, "it4wins511": 0, "champion_id": 245, "it3tot511": 2, "it2wins511": 2, "it1winrate511": 0.46153846153846156, "it4tot511": 0, "it5tot511": 0, "it0tot511": 19, "it2tot511": 5, "name": "Ekko", "matchversion": "5.11", "it5winrate511": 0, "it2winrate511": 0.4, "it1wins511": 6, "it0winrate511": 0.47368421052631576}, {"version": "6.1.1", "it4winrate511": 0.0, "it3winrate511": 0.3333333333333333, "it1tot511": 57, "it0wins511": 41, "it3wins511": 1, "it5wins511": 1, "it4wins511": 0, "champion_id": 9, "it3tot511": 3, "it2wins511": 23, "it1winrate511": 0.6140350877192983, "it4tot511": 1, "it5tot511": 2, "it0tot511": 91, "it2tot511": 38, "name": "Fiddlesticks", "matchversion": "5.11", "it5winrate511": 0.5, "it2winrate511": 0.6052631578947368, "it1wins511": 35, "it0winrate511": 0.45054945054945056}, {"version": "6.1.1", "it4winrate511": 0, "it3winrate511": 0, "it1tot511": 3, "it0wins511": 4, "it3wins511": 0, "it5wins511": 0, "it4wins511": 0, "champion_id": 44, "it3tot511": 0, "it2wins511": 1, "it1winrate511": 0.3333333333333333, "it4tot511": 0, "it5tot511": 0, "it0tot511": 7, "it2tot511": 1, "name": "Taric", "matchversion": "5.11", "it5winrate511": 0, "it2winrate511": 1.0, "it1wins511": 1, "it0winrate511": 0.5714285714285714}, {"version": "6.1.1", "it4winrate511": 0.0, "it3winrate511": 0, "it1tot511": 2, "it0wins511": 2, "it3wins511": 0, "it5wins511": 0, "it4wins511": 0, "champion_id": 90, "it3tot511": 0, "it2wins511": 0, "it1winrate511": 1.0, "it4tot511": 1, "it5tot511": 0, "it0tot511": 7, "it2tot511": 0, "name": "Malzahar", "matchversion": "5.11", "it5winrate511": 0, "it2winrate511": 0, "it1wins511": 2, "it0winrate511": 0.2857142857142857}, {"version": "6.1.1", "it4winrate511": 0.8, "it3winrate511": 0.5376344086021505, "it1tot511": 580, "it0wins511": 919, "it3wins511": 50, "it5wins511": 12, "it4wins511": 24, "champion_id": 267, "it3tot511": 93, "it2wins511": 195, "it1winrate511": 0.5741379310344827, "it4tot511": 30, "it5tot511": 25, "it0tot511": 1725, "it2tot511": 383, "name": "Nami", "matchversion": "5.11", "it5winrate511": 0.48, "it2winrate511": 0.5091383812010444, "it1wins511": 333, "it0winrate511": 0.5327536231884058}, {"version": "6.1.1", "it4winrate511": 0.0, "it3winrate511": 0.3333333333333333, "it1tot511": 80, "it0wins511": 143, "it3wins511": 3, "it5wins511": 2, "it4wins511": 0, "champion_id": 16, "it3tot511": 9, "it2wins511": 33, "it1winrate511": 0.5375, "it4tot511": 1, "it5tot511": 3, "it0tot511": 255, "it2tot511": 59, "name": "Soraka", "matchversion": "5.11", "it5winrate511": 0.6666666666666666, "it2winrate511": 0.559322033898305, "it1wins511": 43, "it0winrate511": 0.5607843137254902}, {"version": "6.1.1", "it4winrate511": 0, "it3winrate511": 0, "it1tot511": 10, "it0wins511": 11, "it3wins511": 0, "it5wins511": 0, "it4wins511": 0, "champion_id": 45, "it3tot511": 0, "it2wins511": 1, "it1winrate511": 0.6, "it4tot511": 0, "it5tot511": 0, "it0tot511": 28, "it2tot511": 1, "name": "Veigar", "matchversion": "5.11", "it5winrate511": 0, "it2winrate511": 1.0, "it1wins511": 6, "it0winrate511": 0.39285714285714285}, {"version": "6.1.1", "it4winrate511": 0.25, "it3winrate511": 0.675, "it1tot511": 322, "it0wins511": 485, "it3wins511": 27, "it5wins511": 2, "it4wins511": 3, "champion_id": 40, "it3tot511": 40, "it2wins511": 128, "it1winrate511": 0.6180124223602484, "it4tot511": 12, "it5tot511": 3, "it0tot511": 881, "it2tot511": 213, "name": "Janna", "matchversion": "5.11", "it5winrate511": 0.6666666666666666, "it2winrate511": 0.6009389671361502, "it1wins511": 199, "it0winrate511": 0.5505107832009081}, {"version": "6.1.1", "it4winrate511": 1.0, "it3winrate511": 0, "it1tot511": 9, "it0wins511": 2, "it3wins511": 0, "it5wins511": 0, "it4wins511": 1, "champion_id": 79, "it3tot511": 0, "it2wins511": 1, "it1winrate511": 0.4444444444444444, "it4tot511": 1, "it5tot511": 0, "it0tot511": 15, "it2tot511": 3, "name": "Gragas", "matchversion": "5.11", "it5winrate511": 0, "it2winrate511": 0.3333333333333333, "it1wins511": 4, "it0winrate511": 0.13333333333333333}, {"version": "6.1.1", "it4winrate511": 0.6206896551724138, "it3winrate511": 0.5074626865671642, "it1tot511": 405, "it0wins511": 634, "it3wins511": 34, "it5wins511": 8, "it4wins511": 18, "champion_id": 117, "it3tot511": 67, "it2wins511": 164, "it1winrate511": 0.528395061728395, "it4tot511": 29, "it5tot511": 18, "it0tot511": 1220, "it2tot511": 301, "name": "Lulu", "matchversion": "5.11", "it5winrate511": 0.4444444444444444, "it2winrate511": 0.5448504983388704, "it1wins511": 214, "it0winrate511": 0.519672131147541}, {"version": "6.1.1", "it4winrate511": 0, "it3winrate511": 0.0, "it1tot511": 6, "it0wins511": 5, "it3wins511": 0, "it5wins511": 1, "it4wins511": 0, "champion_id": 103, "it3tot511": 1, "it2wins511": 1, "it1winrate511": 0.6666666666666666, "it4tot511": 0, "it5tot511": 1, "it0tot511": 7, "it2tot511": 2, "name": "Ahri", "matchversion": "5.11", "it5winrate511": 1.0, "it2winrate511": 0.5, "it1wins511": 4, "it0winrate511": 0.7142857142857143}, {"version": "6.1.1", "it4winrate511": 1.0, "it3winrate511": 0.75, "it1tot511": 13, "it0wins511": 25, "it3wins511": 3, "it5wins511": 0, "it4wins511": 1, "champion_id": 7, "it3tot511": 4, "it2wins511": 3, "it1winrate511": 0.5384615384615384, "it4tot511": 1, "it5tot511": 0, "it0tot511": 35, "it2tot511": 8, "name": "LeBlanc", "matchversion": "5.11", "it5winrate511": 0, "it2winrate511": 0.375, "it1wins511": 7, "it0winrate511": 0.7142857142857143}]