[{"it5tot514": 4, "it5wins514": 4, "name": "Rammus", "it3wins514": 4, "it4wins514": 8, "it3tot514": 7, "champion_id": 33, "matchversion": "5.14", "it0tot514": 0, "version": "6.1.1", "it2wins514": 2, "it0wins514": 0, "it4tot514": 11, "it2tot514": 2, "it1tot514": 2, "region": "RU", "it1wins514": 2}, {"it5tot514": 26, "it5wins514": 18, "name": "Malphite", "it3wins514": 36, "it4wins514": 33, "it3tot514": 64, "champion_id": 54, "matchversion": "5.14", "it0tot514": 26, "version": "6.1.1", "it2wins514": 29, "it0wins514": 14, "it4tot514": 45, "it2tot514": 43, "it1tot514": 42, "region": "RU", "it1wins514": 25}, {"it5tot514": 1, "it5wins514": 1, "name": "Karthus", "it3wins514": 2, "it4wins514": 2, "it3tot514": 3, "champion_id": 30, "matchversion": "5.14", "it0tot514": 1, "version": "6.1.1", "it2wins514": 1, "it0wins514": 0, "it4tot514": 9, "it2tot514": 2, "it1tot514": 0, "region": "RU", "it1wins514": 0}, {"it5tot514": 9, "it5wins514": 8, "name": "Sejuani", "it3wins514": 3, "it4wins514": 3, "it3tot514": 5, "champion_id": 113, "matchversion": "5.14", "it0tot514": 1, "version": "6.1.1", "it2wins514": 4, "it0wins514": 1, "it4tot514": 7, "it2tot514": 8, "it1tot514": 4, "region": "RU", "it1wins514": 2}, {"it5tot514": 2, "it5wins514": 0, "name": "Fizz", "it3wins514": 3, "it4wins514": 6, "it3tot514": 7, "champion_id": 105, "matchversion": "5.14", "it0tot514": 3, "version": "6.1.1", "it2wins514": 12, "it0wins514": 1, "it4tot514": 8, "it2tot514": 12, "it1tot514": 5, "region": "RU", "it1wins514": 2}, {"it5tot514": 5, "it5wins514": 4, "name": "Kassadin", "it3wins514": 3, "it4wins514": 2, "it3tot514": 8, "champion_id": 38, "matchversion": "5.14", "it0tot514": 0, "version": "6.1.1", "it2wins514": 0, "it0wins514": 0, "it4tot514": 3, "it2tot514": 1, "it1tot514": 1, "region": "RU", "it1wins514": 0}, {"it5tot514": 5, "it5wins514": 2, "name": "Viktor", "it3wins514": 3, "it4wins514": 5, "it3tot514": 3, "champion_id": 112, "matchversion": "5.14", "it0tot514": 2, "version": "6.1.1", "it2wins514": 3, "it0wins514": 1, "it4tot514": 8, "it2tot514": 10, "it1tot514": 6, "region": "RU", "it1wins514": 4}, {"it5tot514": 3, "it5wins514": 1, "name": "Maokai", "it3wins514": 5, "it4wins514": 4, "it3tot514": 9, "champion_id": 57, "matchversion": "5.14", "it0tot514": 0, "version": "6.1.1", "it2wins514": 1, "it0wins514": 0, "it4tot514": 7, "it2tot514": 2, "it1tot514": 1, "region": "RU", "it1wins514": 1}, {"it5tot514": 6, "it5wins514": 3, "name": "Akali", "it3wins514": 10, "it4wins514": 10, "it3tot514": 20, "champion_id": 84, "matchversion": "5.14", "it0tot514": 3, "version": "6.1.1", "it2wins514": 6, "it0wins514": 0, "it4tot514": 12, "it2tot514": 9, "it1tot514": 9, "region": "RU", "it1wins514": 6}, {"it5tot514": 5, "it5wins514": 5, "name": "Kennen", "it3wins514": 8, "it4wins514": 5, "it3tot514": 9, "champion_id": 85, "matchversion": "5.14", "it0tot514": 7, "version": "6.1.1", "it2wins514": 1, "it0wins514": 3, "it4tot514": 7, "it2tot514": 5, "it1tot514": 7, "region": "RU", "it1wins514": 6}, {"it5tot514": 0, "it5wins514": 0, "name": "Ryze", "it3wins514": 4, "it4wins514": 3, "it3tot514": 10, "champion_id": 13, "matchversion": "5.14", "it0tot514": 2, "version": "6.1.1", "it2wins514": 1, "it0wins514": 1, "it4tot514": 5, "it2tot514": 1, "it1tot514": 2, "region": "RU", "it1wins514": 1}, {"it5tot514": 7, "it5wins514": 6, "name": "Cho'Gath", "it3wins514": 2, "it4wins514": 8, "it3tot514": 2, "champion_id": 31, "matchversion": "5.14", "it0tot514": 2, "version": "6.1.1", "it2wins514": 1, "it0wins514": 0, "it4tot514": 12, "it2tot514": 2, "it1tot514": 5, "region": "RU", "it1wins514": 3}, {"it5tot514": 5, "it5wins514": 3, "name": "Morgana", "it3wins514": 10, "it4wins514": 12, "it3tot514": 14, "champion_id": 25, "matchversion": "5.14", "it0tot514": 9, "version": "6.1.1", "it2wins514": 4, "it0wins514": 7, "it4tot514": 20, "it2tot514": 9, "it1tot514": 6, "region": "RU", "it1wins514": 2}, {"it5tot514": 1, "it5wins514": 1, "name": "Rumble", "it3wins514": 5, "it4wins514": 3, "it3tot514": 8, "champion_id": 68, "matchversion": "5.14", "it0tot514": 0, "version": "6.1.1", "it2wins514": 1, "it0wins514": 0, "it4tot514": 7, "it2tot514": 2, "it1tot514": 3, "region": "RU", "it1wins514": 1}, {"it5tot514": 2, "it5wins514": 1, "name": "Teemo", "it3wins514": 5, "it4wins514": 2, "it3tot514": 7, "champion_id": 17, "matchversion": "5.14", "it0tot514": 2, "version": "6.1.1", "it2wins514": 1, "it0wins514": 1, "it4tot514": 3, "it2tot514": 2, "it1tot514": 0, "region": "RU", "it1wins514": 0}, {"it5tot514": 12, "it5wins514": 5, "name": "Amumu", "it3wins514": 28, "it4wins514": 18, "it3tot514": 37, "champion_id": 32, "matchversion": "5.14", "it0tot514": 3, "version": "6.1.1", "it2wins514": 20, "it0wins514": 2, "it4tot514": 33, "it2tot514": 28, "it1tot514": 20, "region": "RU", "it1wins514": 11}, {"it5tot514": 1, "it5wins514": 0, "name": "Galio", "it3wins514": 6, "it4wins514": 1, "it3tot514": 9, "champion_id": 3, "matchversion": "5.14", "it0tot514": 3, "version": "6.1.1", "it2wins514": 2, "it0wins514": 2, "it4tot514": 5, "it2tot514": 3, "it1tot514": 5, "region": "RU", "it1wins514": 4}, {"it5tot514": 83, "it5wins514": 45, "name": "Diana", "it3wins514": 99, "it4wins514": 95, "it3tot514": 172, "champion_id": 131, "matchversion": "5.14", "it0tot514": 48, "version": "6.1.1", "it2wins514": 49, "it0wins514": 28, "it4tot514": 157, "it2tot514": 104, "it1tot514": 119, "region": "RU", "it1wins514": 63}, {"it5tot514": 21, "it5wins514": 10, "name": "Elise", "it3wins514": 21, "it4wins514": 19, "it3tot514": 31, "champion_id": 60, "matchversion": "5.14", "it0tot514": 5, "version": "6.1.1", "it2wins514": 7, "it0wins514": 5, "it4tot514": 35, "it2tot514": 12, "it1tot514": 15, "region": "RU", "it1wins514": 8}, {"it5tot514": 22, "it5wins514": 16, "name": "Katarina", "it3wins514": 35, "it4wins514": 36, "it3tot514": 56, "champion_id": 55, "matchversion": "5.14", "it0tot514": 15, "version": "6.1.1", "it2wins514": 42, "it0wins514": 9, "it4tot514": 57, "it2tot514": 68, "it1tot514": 43, "region": "RU", "it1wins514": 21}, {"it5tot514": 15, "it5wins514": 10, "name": "Ekko", "it3wins514": 11, "it4wins514": 12, "it3tot514": 24, "champion_id": 245, "matchversion": "5.14", "it0tot514": 6, "version": "6.1.1", "it2wins514": 13, "it0wins514": 4, "it4tot514": 25, "it2tot514": 23, "it1tot514": 16, "region": "RU", "it1wins514": 6}, {"it5tot514": 9, "it5wins514": 5, "name": "Tahm Kench", "it3wins514": 3, "it4wins514": 2, "it3tot514": 5, "champion_id": 223, "matchversion": "5.14", "it0tot514": 3, "version": "6.1.1", "it2wins514": 4, "it0wins514": 1, "it4tot514": 6, "it2tot514": 11, "it1tot514": 6, "region": "RU", "it1wins514": 4}, {"it5tot514": 5, "it5wins514": 2, "name": "Fiddlesticks", "it3wins514": 7, "it4wins514": 6, "it3tot514": 13, "champion_id": 9, "matchversion": "5.14", "it0tot514": 5, "version": "6.1.1", "it2wins514": 6, "it0wins514": 1, "it4tot514": 14, "it2tot514": 7, "it1tot514": 8, "region": "RU", "it1wins514": 4}, {"it5tot514": 3, "it5wins514": 0, "name": "Lissandra", "it3wins514": 5, "it4wins514": 4, "it3tot514": 8, "champion_id": 127, "matchversion": "5.14", "it0tot514": 5, "version": "6.1.1", "it2wins514": 2, "it0wins514": 1, "it4tot514": 7, "it2tot514": 6, "it1tot514": 2, "region": "RU", "it1wins514": 1}, {"it5tot514": 9, "it5wins514": 6, "name": "Vladimir", "it3wins514": 9, "it4wins514": 3, "it3tot514": 17, "champion_id": 8, "matchversion": "5.14", "it0tot514": 1, "version": "6.1.1", "it2wins514": 7, "it0wins514": 1, "it4tot514": 7, "it2tot514": 14, "it1tot514": 9, "region": "RU", "it1wins514": 3}, {"it5tot514": 14, "it5wins514": 10, "name": "Nautilus", "it3wins514": 23, "it4wins514": 13, "it3tot514": 42, "champion_id": 111, "matchversion": "5.14", "it0tot514": 16, "version": "6.1.1", "it2wins514": 17, "it0wins514": 8, "it4tot514": 29, "it2tot514": 25, "it1tot514": 22, "region": "RU", "it1wins514": 12}, {"it5tot514": 2, "it5wins514": 1, "name": "Evelynn", "it3wins514": 5, "it4wins514": 4, "it3tot514": 11, "champion_id": 28, "matchversion": "5.14", "it0tot514": 1, "version": "6.1.1", "it2wins514": 4, "it0wins514": 1, "it4tot514": 6, "it2tot514": 5, "it1tot514": 1, "region": "RU", "it1wins514": 0}, {"it5tot514": 10, "it5wins514": 6, "name": "Ahri", "it3wins514": 10, "it4wins514": 12, "it3tot514": 20, "champion_id": 103, "matchversion": "5.14", "it0tot514": 7, "version": "6.1.1", "it2wins514": 4, "it0wins514": 5, "it4tot514": 16, "it2tot514": 10, "it1tot514": 9, "region": "RU", "it1wins514": 6}]