[{"it3wins511": 13, "it4tot511": 11, "matchversion": "5.11", "name": "Kayle", "it5wins511": 4, "it4wins511": 8, "region": "EUW", "champion_id": 10, "it3tot511": 20, "it2tot511": 39, "it2wins511": 23, "it0tot511": 15, "version": "6.1.1", "it1tot511": 56, "it1wins511": 23, "it0wins511": 5, "it5tot511": 7}, {"it3wins511": 12, "it4tot511": 18, "matchversion": "5.11", "name": "Azir", "it5wins511": 8, "it4wins511": 15, "region": "EUW", "champion_id": 268, "it3tot511": 28, "it2tot511": 36, "it2wins511": 22, "it0tot511": 18, "version": "6.1.1", "it1tot511": 25, "it1wins511": 9, "it0wins511": 13, "it5tot511": 10}, {"it3wins511": 64, "it4tot511": 79, "matchversion": "5.11", "name": "Teemo", "it5wins511": 16, "it4wins511": 47, "region": "EUW", "champion_id": 17, "it3tot511": 111, "it2tot511": 145, "it2wins511": 85, "it0tot511": 91, "version": "6.1.1", "it1tot511": 182, "it1wins511": 99, "it0wins511": 44, "it5tot511": 27}, {"it3wins511": 21, "it4tot511": 31, "matchversion": "5.11", "name": "Diana", "it5wins511": 9, "it4wins511": 19, "region": "EUW", "champion_id": 131, "it3tot511": 38, "it2tot511": 35, "it2wins511": 17, "it0tot511": 14, "version": "6.1.1", "it1tot511": 28, "it1wins511": 15, "it0wins511": 6, "it5tot511": 12}, {"it3wins511": 15, "it4tot511": 32, "matchversion": "5.11", "name": "Ekko", "it5wins511": 7, "it4wins511": 16, "region": "EUW", "champion_id": 245, "it3tot511": 26, "it2tot511": 23, "it2wins511": 13, "it0tot511": 18, "version": "6.1.1", "it1tot511": 22, "it1wins511": 15, "it0wins511": 14, "it5tot511": 8}, {"it3wins511": 7, "it4tot511": 2, "matchversion": "5.11", "name": "Xin Zhao", "it5wins511": 1, "it4wins511": 2, "region": "EUW", "champion_id": 5, "it3tot511": 7, "it2tot511": 4, "it2wins511": 2, "it0tot511": 3, "version": "6.1.1", "it1tot511": 5, "it1wins511": 3, "it0wins511": 2, "it5tot511": 1}]